KrypticLogger/__init__.py
KrypticLogger-0.4.dist-info/LICENSE.txt
KrypticLogger-0.4.dist-info/METADATA
KrypticLogger-0.4.dist-info/WHEEL
KrypticLogger-0.4.dist-info/top_level.txt
KrypticLogger-0.4.dist-info/RECORD
