Metadata-Version: 2.1
Name: KrypticLogger
Version: 0.4
Summary: KrypticLogger is a tool to help better organize and minimizing the amount of code while logging! 
Home-page: https://github.com/KrypticStudio/KrypticLogger/
Author: Kryptic Studio
Author-email: kennethc@kryptic-studio.com
License: UNKNOWN
Platform: UNKNOWN
Classifier: Programming Language :: Python :: 3
Classifier: License :: OSI Approved :: MIT License
Classifier: Operating System :: OS Independent
